{
  "version": "https://jsonfeed.org/version/1.1",
  "title": "Terry Script",
  "language": "en",
  "home_page_url": "https://terryscript.dev/",
  "feed_url": "https://terryscript.dev/feed/feed.json",
  "description": "Terry Smith&#39;s personal site, lead developer @codecov.",
  "author": {
    "name": "Terry Smith",
    "url": "https://terryscript.dev/about-me/"
  },
  "items": [{
      "id": "https://terryscript.dev/posts/test2/",
      "url": "https://terryscript.dev/posts/test2/",
      "title": "Test 2",
      "content_html": "<p>Lorem ipsum dolor sit amet, consectetur adipiscing elit. Donec sit amet est placerat, tincidunt turpis quis, tempor velit. Cras finibus varius enim, non tincidunt dui dapibus at. Curabitur ut sagittis odio. Aenean ac orci non quam tincidunt dignissim ac a urna. Pellentesque commodo tristique magna a elementum. Suspendisse euismod quam id placerat suscipit. Sed pretium fringilla ligula, in consequat est accumsan tempus. Mauris turpis metus, vehicula ut orci non, auctor tempor dolor. Cras molestie tortor et cursus luctus. Ut porttitor eros vitae dolor elementum porttitor eu id tellus. Aliquam aliquet magna nisl, quis suscipit nibh porta laoreet. Etiam euismod non leo eget blandit. Vestibulum mattis scelerisque mollis. Duis porta commodo sollicitudin. Duis mollis velit molestie mauris dignissim dignissim.</p>\n<p>Proin quam orci, malesuada auctor tempus vel, ornare non libero. Morbi at egestas felis. Nam quis risus euismod, vehicula nisl non, suscipit augue. Nullam risus orci, finibus non lorem vel, dignissim hendrerit tellus. Morbi id nisi in orci varius rhoncus. Fusce a sapien sodales, gravida augue sed, dignissim risus. Ut eget lectus maximus, ultrices purus in, bibendum velit. Praesent vel enim et purus imperdiet condimentum at sit amet purus. Nam et nisi vel turpis feugiat ornare. Proin lorem elit, sagittis in tempus non, iaculis eget nunc. Aenean eu enim sed nunc sagittis mollis. Aliquam orci ipsum, porttitor eu eleifend id, fringilla non justo. Aliquam accumsan viverra tortor. Integer non mattis ligula, eget imperdiet sapien.</p>\n<h2 id=\"rabble-rabble\" class=\"group anchor-offset\">\n  <span>Rabble Rabble</span>\n  <a class=\"transition duration-200 ease-in-out opacity-0 group-hover:opacity-100 \" href=\"https://terryscript.dev/posts/test2/#rabble-rabble\">#</a>\n</h2>\n<p>Etiam feugiat rhoncus quam, at accumsan velit accumsan ut. Sed ultrices elit vel tellus tincidunt, ac viverra erat finibus. Mauris vel laoreet nunc. Maecenas dapibus risus nec hendrerit pharetra. Nulla sollicitudin, arcu et accumsan ultrices, ex ligula imperdiet lectus, eu suscipit justo dui nec purus. Integer finibus sapien ut nibh sodales, suscipit convallis elit aliquet. Maecenas convallis justo a ligula suscipit consequat. Fusce volutpat consequat quam, in pulvinar urna malesuada in.</p>\n<p>Aliquam erat volutpat. Nullam condimentum sodales fermentum. Phasellus vitae vestibulum arcu. Donec auctor eleifend metus sed imperdiet. Duis non pulvinar justo. Ut neque enim, sodales maximus nisl sit amet, accumsan rhoncus dui. Nulla urna tellus, pellentesque ut vulputate et, scelerisque at metus. Nulla faucibus elit eu ex luctus ultrices. Curabitur interdum, nisl eget pretium fermentum, erat neque euismod risus, id gravida leo mauris et purus. Etiam ullamcorper viverra consequat. Duis mollis, massa non porttitor congue, leo risus commodo sapien, vel faucibus turpis odio ac nisi. Morbi ut ex sit amet metus euismod euismod ac ac odio. Vivamus placerat leo ac lorem sodales, sed placerat est facilisis. Pellentesque habitant morbi tristique senectus et netus et malesuada fames ac turpis egestas. Sed viverra interdum dui, ut mollis erat pharetra nec. Morbi porttitor, sem ut maximus euismod, sapien ipsum aliquet eros, ac fermentum ligula ante eu nunc.</p>\n<p>Vivamus at nisl nisl. Aliquam eget interdum velit. Donec mollis enim ac blandit dictum. Curabitur in eros dignissim turpis semper ullamcorper. Duis aliquet elementum pulvinar. Sed commodo suscipit turpis nec eleifend. Nam tristique pharetra nisl eget imperdiet. In convallis laoreet dui, eget egestas dui eleifend vitae. Morbi tellus dolor, convallis eget imperdiet a, malesuada ac magna. Orci varius natoque penatibus et magnis dis parturient montes, nascetur ridiculus mus. In est odio, sagittis at orci at, posuere mollis turpis. Morbi porttitor lectus sit amet risus laoreet, ut bibendum nisl vulputate. Donec non efficitur dolor. Donec accumsan convallis risus non aliquet.</p>\n",
      "date_published": "2018-05-01T00:00:00Z"
    },{
      "id": "https://terryscript.dev/posts/test/",
      "url": "https://terryscript.dev/posts/test/",
      "title": "Style Guide",
      "content_html": "<section class=\"container my-10 md:my-14\">\n<h1>This is the Style Guide page.</h1>\n<h2>This is the Style Guide page.</h2>\n<h3>This is the Style Guide page.</h3>\n<h4>This is the Style Guide page.</h4>\n<h5>This is the Style Guide page.</h5>\n<h6>This is the Style Guide page.</h6>\n<p>Lorem ipsum dolor sit amet, consectetur adipiscing elit. Vivamus volutpat ut nunc ut porta. Vivamus ultrices tristique turpis, in accumsan nunc vestibulum non. Ut sed urna sit amet enim accumsan eleifend. Praesent sodales mi laoreet justo ultricies ullamcorper. Morbi dignissim felis neque, sodales elementum nulla interdum a. Pellentesque tincidunt porttitor nisl a iaculis. Vestibulum aliquam massa elit, eget semper lacus suscipit sit amet. Mauris ullamcorper vulputate urna a sollicitudin. Aenean id diam maximus, ultrices enim vitae, euismod lacus. Aliquam tristique porttitor risus sit amet mollis. Nullam vitae viverra felis.</p>\n<h5>Text styles:</h5>\n<p>I just love <strong>bold text</strong>.</p>\n<p>Italicized text is the <em>cat's meow</em>.</p>\n<p>This text is <strong><em>really important</em></strong>.</p>\n<h5>Blockquotes</h5>\n<blockquote>\n<p>Dorothy followed her through many of the beautiful rooms in her castle.</p>\n</blockquote>\n<blockquote>\n<p>Dorothy followed her through many of the beautiful rooms in her castle.</p>\n<p>The Witch bade her clean the pots and kettles and sweep the floor and keep the fire fed with wood.</p>\n</blockquote>\n<blockquote>\n<p>Dorothy followed her through many of the beautiful rooms in her castle.</p>\n<blockquote>\n<p>The Witch bade her clean the pots and kettles and sweep the floor and keep the fire fed with wood.</p>\n</blockquote>\n</blockquote>\n<blockquote>\n<h6>The quarterly results look great!</h6>\n<ul>\n<li>\n<p>Revenue was off the chart.</p>\n</li>\n<li>\n<p>Profits were higher than ever.</p>\n<p><em>Everything</em> is going according to <strong>plan</strong>.</p>\n</li>\n</ul>\n</blockquote>\n<h5>Lists</h5>\n<h6>Ordered:</h6>\n<ol>\n<li>First item</li>\n<li>Second item</li>\n<li>Third item\n<ol>\n<li>Indented item</li>\n<li>Indented item</li>\n</ol>\n</li>\n<li>Fourth item</li>\n</ol>\n<h6>Unordered:</h6>\n<ul>\n<li>First item</li>\n<li>Second item</li>\n<li>Third item\n<ul>\n<li>Indented item</li>\n<li>Indented item</li>\n</ul>\n</li>\n<li>Fourth item</li>\n</ul>\n<h5>Code</h5>\n<p><code>const foo = 'bar'</code></p>\n<h5>Misc</h5>\n<hr />\n<p>My favorite search engine is <a href=\"https://duckduckgo.com/\">Duck Duck Go</a>.</p>\n<h5>TODO...</h5>\n<p><button>I do nothing!</button></p>\n<p><button disabled=\"\">I 'm disabled'!</button></p>\n<input placeholder=\"Input\" />\n</section>\n",
      "date_published": "2018-05-01T00:00:00Z"
    }
  ]
}